vjtube/__init__.py
vjtube/scraper.py
vjtube/utils.py
vjtube-1.0.1.dist-info/METADATA
vjtube-1.0.1.dist-info/WHEEL
vjtube-1.0.1.dist-info/top_level.txt
vjtube-1.0.1.dist-info/RECORD
