Metadata-Version: 2.1
Name: vjtube
Version: 1.0.1
Summary: Uma biblioteca para realizar scraping de vídeos do YouTube procurando usos indevidos de sua música.
Home-page: https://github.com/Fioruci/vjtube
Author: Felipe Fioruci
Author-email: felipe.fioruci@vjbots.com.br
Classifier: Programming Language :: Python :: 3
Classifier: License :: OSI Approved :: MIT License
Classifier: Operating System :: OS Independent
Requires-Python: >=3.6
Requires-Dist: playwright
